atomdriver/__init__.py
atomdriver/abstract_driver.py
atomdriver/accessors.py
atomdriver/context.py
atomdriver/exceptions.py
atomdriver/project.py
atomdriver/properties.py
atomdriver/registry.yaml
atomdriver/util.py
atomdriver/drivers/__init__.py
atomdriver/drivers/cp2k.py
atomdriver/drivers/gamess.py
atomdriver/drivers/libxtb.py
atomdriver/drivers/mopac.py
atomdriver/drivers/nwchem.py
atomdriver/drivers/orca.py
atomdriver/drivers/pyscf.py
atomdriver/drivers/qchem.py
atomdriver/drivers/xtb.py
atomdriver/drivers/xtbcommon.py
atomdriver_qc-0.1.4.dist-info/METADATA
atomdriver_qc-0.1.4.dist-info/WHEEL
atomdriver_qc-0.1.4.dist-info/top_level.txt
atomdriver_qc-0.1.4.dist-info/RECORD
